[{"rdmt":["https://w3id.org/016f1","https://w3id.org/16ca7"],"rdm":["https://w3id.org/016f1","https://w3id.org/16ca7"],"rd":["https://w3id.org/016f1","https://w3id.org/16ca7"],"r":["https://w3id.org/016f1","https://w3id.org/16ca7"],"dmt":["https://w3id.org/016f1","https://w3id.org/16ca7"],"dm":["https://w3id.org/016f1","https://w3id.org/16ca7"],"d":["https://w3id.org/016f1","https://w3id.org/16ca7"],"mt":["https://w3id.org/016f1","https://w3id.org/16ca7"],"m":["https://w3id.org/016f1","https://w3id.org/16ca7"],"t":["https://w3id.org/016f1","https://w3id.org/16ca7"]},{"training":["https://w3id.org/016f1"],"trainin":["https://w3id.org/016f1"],"traini":["https://w3id.org/016f1"],"train":["https://w3id.org/016f1"],"trai":["https://w3id.org/016f1"],"tra":["https://w3id.org/016f1"],"tr":["https://w3id.org/016f1"],"teaching":["https://w3id.org/16ca7"],"teachin":["https://w3id.org/16ca7"],"teachi":["https://w3id.org/16ca7"],"teach":["https://w3id.org/16ca7"],"teac":["https://w3id.org/16ca7"],"tea":["https://w3id.org/16ca7"],"te":["https://w3id.org/16ca7"]},{"raining":["https://w3id.org/016f1"],"rainin":["https://w3id.org/016f1"],"raini":["https://w3id.org/016f1"],"rain":["https://w3id.org/016f1"],"rai":["https://w3id.org/016f1"],"ra":["https://w3id.org/016f1"],"formats":["https://w3id.org/016f1"],"format":["https://w3id.org/016f1"],"forma":["https://w3id.org/016f1"],"form":["https://w3id.org/016f1"],"for":["https://w3id.org/016f1"],"fo":["https://w3id.org/016f1"],"f":["https://w3id.org/016f1"],"eaching":["https://w3id.org/16ca7"],"eachin":["https://w3id.org/16ca7"],"eachi":["https://w3id.org/16ca7"],"each":["https://w3id.org/16ca7"],"eac":["https://w3id.org/16ca7"],"ea":["https://w3id.org/16ca7"],"e":["https://w3id.org/16ca7"],"materials":["https://w3id.org/16ca7"],"material":["https://w3id.org/16ca7"],"materia":["https://w3id.org/16ca7"],"materi":["https://w3id.org/16ca7"],"mater":["https://w3id.org/16ca7"],"mate":["https://w3id.org/16ca7"],"mat":["https://w3id.org/16ca7"],"ma":["https://w3id.org/16ca7"]},{"aining":["https://w3id.org/016f1"],"ainin":["https://w3id.org/016f1"],"aini":["https://w3id.org/016f1"],"ain":["https://w3id.org/016f1"],"ai":["https://w3id.org/016f1"],"a":["https://w3id.org/016f1","https://w3id.org/16ca7"],"ining":["https://w3id.org/016f1"],"inin":["https://w3id.org/016f1"],"ini":["https://w3id.org/016f1"],"in":["https://w3id.org/016f1"],"i":["https://w3id.org/016f1"],"ormats":["https://w3id.org/016f1"],"ormat":["https://w3id.org/016f1"],"orma":["https://w3id.org/016f1"],"orm":["https://w3id.org/016f1"],"or":["https://w3id.org/016f1"],"o":["https://w3id.org/016f1"],"aching":["https://w3id.org/16ca7"],"achin":["https://w3id.org/16ca7"],"achi":["https://w3id.org/16ca7"],"ach":["https://w3id.org/16ca7"],"ac":["https://w3id.org/16ca7"],"ching":["https://w3id.org/16ca7"],"chin":["https://w3id.org/16ca7"],"chi":["https://w3id.org/16ca7"],"ch":["https://w3id.org/16ca7"],"c":["https://w3id.org/16ca7"],"aterials":["https://w3id.org/16ca7"],"aterial":["https://w3id.org/16ca7"],"ateria":["https://w3id.org/16ca7"],"ateri":["https://w3id.org/16ca7"],"ater":["https://w3id.org/16ca7"],"ate":["https://w3id.org/16ca7"],"at":["https://w3id.org/16ca7"],"terials":["https://w3id.org/16ca7"],"terial":["https://w3id.org/16ca7"],"teria":["https://w3id.org/16ca7"],"teri":["https://w3id.org/16ca7"],"ter":["https://w3id.org/16ca7"]},{"ning":["https://w3id.org/016f1"],"nin":["https://w3id.org/016f1"],"ni":["https://w3id.org/016f1"],"n":["https://w3id.org/016f1"],"rmats":["https://w3id.org/016f1"],"rmat":["https://w3id.org/016f1"],"rma":["https://w3id.org/016f1"],"rm":["https://w3id.org/016f1"],"hing":["https://w3id.org/16ca7"],"hin":["https://w3id.org/16ca7"],"hi":["https://w3id.org/16ca7"],"h":["https://w3id.org/16ca7"],"erials":["https://w3id.org/16ca7"],"erial":["https://w3id.org/16ca7"],"eria":["https://w3id.org/16ca7"],"eri":["https://w3id.org/16ca7"],"er":["https://w3id.org/16ca7"]},{"ing":["https://w3id.org/016f1","https://w3id.org/16ca7"],"mats":["https://w3id.org/016f1"],"mat":["https://w3id.org/016f1"],"ma":["https://w3id.org/016f1"],"ats":["https://w3id.org/016f1"],"at":["https://w3id.org/016f1"],"in":["https://w3id.org/16ca7"],"i":["https://w3id.org/16ca7"],"rials":["https://w3id.org/16ca7"],"rial":["https://w3id.org/16ca7"],"ria":["https://w3id.org/16ca7"],"ri":["https://w3id.org/16ca7"],"ials":["https://w3id.org/16ca7"],"ial":["https://w3id.org/16ca7"],"ia":["https://w3id.org/16ca7"]},{"ng":["https://w3id.org/016f1","https://w3id.org/16ca7"],"g":["https://w3id.org/016f1","https://w3id.org/16ca7"],"ts":["https://w3id.org/016f1"],"n":["https://w3id.org/16ca7"],"als":["https://w3id.org/16ca7"],"al":["https://w3id.org/16ca7"]},{"s":["https://w3id.org/016f1","https://w3id.org/16ca7"],"ls":["https://w3id.org/16ca7"],"l":["https://w3id.org/16ca7"]},{}]